{
  "personas": [
    {
      "persona_id": "A_NguyenVanAn",
      "full_name_censored": "Nguyễn Văn A***",
      "description": "Hồ sơ ideal - dự kiến duyệt ưu tiên hạng AA",
      "expected_result": "approved_priority",
      "personal_info": {
        "age": 32,
        "gender": "male",
        "marital_status": "married",
        "dependents": 1,
        "education": "bachelor",
        "residency_status": "owner"
      },
      "employment": {
        "employer": "Công ty TNHH FPT Software",
        "job_title": "Kỹ sư phần mềm",
        "employment_contract": "permanent",
        "employment_duration_months": 60,
        "monthly_income_vnd": 25000000,
        "salary_method": "bank_transfer"
      },
      "credit_history": {
        "credit_history_cic": "group1_all_ontime",
        "active_loans_count": 0,
        "credit_history_length_years": 5,
        "dti_current": 0.15
      },
      "assets": {
        "real_estate": "owned_titled",
        "vehicle": "motorbike",
        "savings_vnd": 40000000
      },
      "loan_request": {
        "vehicle_name": "Honda Vision 2025",
        "vehicle_price_vnd": 34000000,
        "down_payment_vnd": 4000000,
        "loan_amount_vnd": 30000000,
        "term_months": 18
      }
    },
    {
      "persona_id": "B_TranThiBinh",
      "full_name_censored": "Trần Thị B***",
      "description": "Hồ sơ borderline - dự kiến xem xét thủ công hạng BB",
      "expected_result": "manual_review",
      "personal_info": {
        "age": 27,
        "gender": "female",
        "marital_status": "single",
        "dependents": 0,
        "education": "bachelor",
        "residency_status": "renting_lt_2y"
      },
      "employment": {
        "employer": "Công ty TNHH Thương mại ABC",
        "job_title": "Kế toán viên",
        "employment_contract": "fixed_gte_12m",
        "employment_duration_months": 8,
        "monthly_income_vnd": 11000000,
        "salary_method": "bank_transfer"
      },
      "credit_history": {
        "credit_history_cic": "group2_once",
        "active_loans_count": 1,
        "credit_history_length_years": 2,
        "dti_current": 0.14
      },
      "assets": {
        "real_estate": "none",
        "vehicle": "motorbike",
        "savings_vnd": 8000000
      },
      "loan_request": {
        "vehicle_name": "Yamaha Janus 2025",
        "vehicle_price_vnd": 30000000,
        "down_payment_vnd": 5000000,
        "loan_amount_vnd": 25000000,
        "term_months": 24
      }
    },
    {
      "persona_id": "C_LeVanCuong",
      "full_name_censored": "Lê Văn C***",
      "description": "Hồ sơ fail - dự kiến từ chối do vi phạm hard rules",
      "expected_result": "rejected",
      "personal_info": {
        "age": 45,
        "gender": "male",
        "marital_status": "divorced_widowed",
        "dependents": 2,
        "education": "highschool",
        "residency_status": "renting_lt_2y"
      },
      "employment": {
        "employer": "Tự do (lái xe công nghệ)",
        "job_title": "Tài xế xe công nghệ",
        "employment_contract": "freelance",
        "employment_duration_months": 24,
        "monthly_income_vnd": 8000000,
        "salary_method": "cash_unverified"
      },
      "credit_history": {
        "credit_history_cic": "group3",
        "active_loans_count": 2,
        "credit_history_length_years": 3,
        "dti_current": 0.30
      },
      "assets": {
        "real_estate": "none",
        "vehicle": "motorbike",
        "savings_vnd": 2000000
      },
      "loan_request": {
        "vehicle_name": "Honda Wave Alpha 2025",
        "vehicle_price_vnd": 50000000,
        "down_payment_vnd": 10000000,
        "loan_amount_vnd": 40000000,
        "term_months": 24
      }
    }
  ]
}
